addition_package/__init__.py
addition_package/operations.py
addition_package_yuwenjun-0.1.0.dist-info/LICENSE
addition_package_yuwenjun-0.1.0.dist-info/METADATA
addition_package_yuwenjun-0.1.0.dist-info/WHEEL
addition_package_yuwenjun-0.1.0.dist-info/top_level.txt
addition_package_yuwenjun-0.1.0.dist-info/RECORD
